{
    "_links": {
        "self": {
            "href": "http:\/\/default\/content\/lorem-ipsum-dolor-sit-amet-16?_format=hal_json"
        },
        "type": {
            "href": "http:\/\/drupal.org\/rest\/type\/node\/contact_us_page_gmap"
        },
        "http:\/\/drupal.org\/rest\/relation\/node\/contact_us_page_gmap\/uid": [
            {
                "href": "http:\/\/default\/users\/admin?_format=hal_json",
                "lang": "en"
            }
        ],
        "http:\/\/drupal.org\/rest\/relation\/node\/contact_us_page_gmap\/revision_uid": [
            {
                "href": "http:\/\/default\/users\/admin?_format=hal_json"
            }
        ]
    },
    "nid": [
        {
            "value": "90"
        }
    ],
    "uuid": [
        {
            "value": "1c899868-89e6-4fee-ab0f-1b48578b4e84"
        }
    ],
    "vid": [
        {
            "value": "90"
        }
    ],
    "langcode": [
        {
            "value": "en",
            "lang": "en"
        }
    ],
    "type": [
        {
            "target_id": "contact_us_page_gmap"
        }
    ],
    "title": [
        {
            "value": "Gmap_block",
            "lang": "en"
        }
    ],
    "_embedded": {
        "http:\/\/drupal.org\/rest\/relation\/node\/contact_us_page_gmap\/uid": [
            {
                "_links": {
                    "self": {
                        "href": "http:\/\/default\/users\/admin?_format=hal_json"
                    },
                    "type": {
                        "href": "http:\/\/drupal.org\/rest\/type\/user\/user"
                    }
                },
                "uuid": [
                    {
                        "value": "7edac145-49a7-4eb3-86da-758606161db9"
                    }
                ],
                "lang": "en"
            }
        ],
        "http:\/\/drupal.org\/rest\/relation\/node\/contact_us_page_gmap\/revision_uid": [
            {
                "_links": {
                    "self": {
                        "href": "http:\/\/default\/users\/admin?_format=hal_json"
                    },
                    "type": {
                        "href": "http:\/\/drupal.org\/rest\/type\/user\/user"
                    }
                },
                "uuid": [
                    {
                        "value": "7edac145-49a7-4eb3-86da-758606161db9"
                    }
                ]
            }
        ]
    },
    "status": [
        {
            "value": "1",
            "lang": "en"
        }
    ],
    "created": [
        {
            "value": "1464930833",
            "lang": "en"
        }
    ],
    "changed": [
        {
            "value": "1465181508",
            "lang": "en"
        }
    ],
    "promote": [
        {
            "value": "0",
            "lang": "en"
        }
    ],
    "sticky": [
        {
            "value": "0",
            "lang": "en"
        }
    ],
    "revision_timestamp": [
        {
            "value": "1464930852"
        }
    ],
    "revision_translation_affected": [
        {
            "value": "1",
            "lang": "en"
        }
    ],
    "default_langcode": [
        {
            "value": "1",
            "lang": "en"
        }
    ],
    "field_gmap": [
        {
            "value": "Saint-Michel - Notre-Dame"
        }
    ]
}